TideZhongwenWendangFix1/README.md
TideZhongwenWendangFix1/__init__.py
TideZhongwenWendangFix1/__main__.py
TideZhongwenWendangFix1/file.epub
TideZhongwenWendangFix1/index.html
TideZhongwenWendangFix1/css/__init__.py
TideZhongwenWendangFix1/css/annotations.css
TideZhongwenWendangFix1/css/main.css
TideZhongwenWendangFix1/css/normalize.css
TideZhongwenWendangFix1/css/popup.css
TideZhongwenWendangFix1/font/__init__.py
TideZhongwenWendangFix1/font/fontello.eot
TideZhongwenWendangFix1/font/fontello.svg
TideZhongwenWendangFix1/font/fontello.ttf
TideZhongwenWendangFix1/font/fontello.woff
TideZhongwenWendangFix1/img/__init__.py
TideZhongwenWendangFix1/img/annotator-glyph-sprite.png
TideZhongwenWendangFix1/img/annotator-icon-sprite.png
TideZhongwenWendangFix1/img/apple-touch-icon.png
TideZhongwenWendangFix1/img/cancelfullscreen.png
TideZhongwenWendangFix1/img/close.png
TideZhongwenWendangFix1/img/fullscreen.png
TideZhongwenWendangFix1/img/loader.gif
TideZhongwenWendangFix1/img/menu-icon.png
TideZhongwenWendangFix1/img/save.png
TideZhongwenWendangFix1/img/saved.png
TideZhongwenWendangFix1/img/settings-s.png
TideZhongwenWendangFix1/img/settings.png
TideZhongwenWendangFix1/img/star.png
TideZhongwenWendangFix1/js/__init__.py
TideZhongwenWendangFix1/js/epub.js
TideZhongwenWendangFix1/js/epub.min.js
TideZhongwenWendangFix1/js/epub.min.map
TideZhongwenWendangFix1/js/hooks.min.js
TideZhongwenWendangFix1/js/hooks.min.map
TideZhongwenWendangFix1/js/reader.js
TideZhongwenWendangFix1/js/reader.js.map
TideZhongwenWendangFix1/js/reader.min.js
TideZhongwenWendangFix1/js/reader.min.map
TideZhongwenWendangFix1/js/hooks/__init__.py
TideZhongwenWendangFix1/js/hooks/extensions/__init__.py
TideZhongwenWendangFix1/js/hooks/extensions/highlight.js
TideZhongwenWendangFix1/js/libs/__init__.py
TideZhongwenWendangFix1/js/libs/jquery.min.js
TideZhongwenWendangFix1/js/libs/localforage.min.js
TideZhongwenWendangFix1/js/libs/screenfull.js
TideZhongwenWendangFix1/js/libs/screenfull.min.js
tide_zhongwen_wendang_fix1-2025.3.25.0.dist-info/METADATA
tide_zhongwen_wendang_fix1-2025.3.25.0.dist-info/WHEEL
tide_zhongwen_wendang_fix1-2025.3.25.0.dist-info/entry_points.txt
tide_zhongwen_wendang_fix1-2025.3.25.0.dist-info/top_level.txt
tide_zhongwen_wendang_fix1-2025.3.25.0.dist-info/RECORD
